dotenv_azd/__about__.py
dotenv_azd/__init__.py
dotenv_azd/py.typed
dotenv_azd-0.3.0.dist-info/METADATA
dotenv_azd-0.3.0.dist-info/WHEEL
dotenv_azd-0.3.0.dist-info/licenses/LICENSE.txt
dotenv_azd-0.3.0.dist-info/RECORD
