Metadata-Version: 2.4
Name: dotenv-azd
Version: 0.3.0
Summary: Python dotenv adapter that loads dotenv key value pairs from Azure Developer CLI (azd)
Project-URL: Documentation, https://github.com/cedricvidal/dotenv-azd#readme
Project-URL: Issues, https://github.com/cedricvidal/dotenv-azd/issues
Project-URL: Source, https://github.com/cedricvidal/dotenv-azd
Author-email: Cedric Vidal <cedric.vidal@gmail.com>
License-Expression: MIT
License-File: LICENSE.txt
Classifier: Development Status :: 4 - Beta
Classifier: Operating System :: MacOS :: MacOS X
Classifier: Operating System :: Microsoft :: Windows
Classifier: Operating System :: POSIX :: Linux
Classifier: Programming Language :: Python
Classifier: Programming Language :: Python :: 3.9
Classifier: Programming Language :: Python :: 3.10
Classifier: Programming Language :: Python :: 3.11
Classifier: Programming Language :: Python :: 3.12
Classifier: Programming Language :: Python :: Implementation :: CPython
Classifier: Programming Language :: Python :: Implementation :: PyPy
Requires-Python: >=3.9
Requires-Dist: python-dotenv
